flumut_gui/LauncherWindow.py
flumut_gui/MainWindow.py
flumut_gui/ProgressWindow.py
flumut_gui/SampleTreeTab.py
flumut_gui/__init__.py
flumut_gui/data/__init__.py
flumut_gui/data/flumut_icon.ico
flumut_gui-3.2.0.dist-info/licenses/LICENSE
flumut_gui-3.2.0.dist-info/METADATA
flumut_gui-3.2.0.dist-info/WHEEL
flumut_gui-3.2.0.dist-info/entry_points.txt
flumut_gui-3.2.0.dist-info/top_level.txt
flumut_gui-3.2.0.dist-info/RECORD
