Metadata-Version: 2.4
Name: flumut_gui
Version: 3.2.0
Summary: Graphical frontend for the FluMut bioinformatic tool
Author-email: Alessandro Sartori <alex.sartori1997@gmail.com>, Edoardo Giussani <egiussani@izsvenezie.it>
License:                     GNU AFFERO GENERAL PUBLIC LICENSE
Project-URL: Homepage, https://izsvenezie-virology.github.io/FluMut
Project-URL: Bug Reports, https://github.com/izsvenezie-virology/FluMutGUI/issues
Project-URL: Source, https://github.com/izsvenezie-virology/FluMutGUI
Keywords: flumut,flumut GUI,molecular markers,Influenza A Virus,AIV
Requires-Python: >=3.7
License-File: LICENSE
Requires-Dist: pyqt5
Requires-Dist: flumut>=0.6.3
Requires-Dist: importlib-resources>=1.3
Dynamic: license-file
